cfunctions/__init__.py
cfunctions/py.typed
cfunctions/_jsii/__init__.py
cfunctions/_jsii/cfunctions@0.1.196.jsii.tgz
cfunctions-0.1.196.dist-info/LICENSE
cfunctions-0.1.196.dist-info/METADATA
cfunctions-0.1.196.dist-info/WHEEL
cfunctions-0.1.196.dist-info/top_level.txt
cfunctions-0.1.196.dist-info/RECORD
