Metadata-Version: 2.1
Name: cfunctions
Version: 0.1.196
Summary: cfunctions
Home-page: https://github.com/eladb/cfunctions.git
Author: Elad Ben-Israel<benisrae@amazon.com>
License: Apache-2.0
Project-URL: Source, https://github.com/eladb/cfunctions.git
Platform: UNKNOWN
Classifier: Intended Audience :: Developers
Classifier: Operating System :: OS Independent
Classifier: Programming Language :: JavaScript
Classifier: Programming Language :: Python :: 3 :: Only
Classifier: Programming Language :: Python :: 3.6
Classifier: Programming Language :: Python :: 3.7
Classifier: Programming Language :: Python :: 3.8
Classifier: Programming Language :: Python :: 3.9
Classifier: Typing :: Typed
Classifier: Development Status :: 5 - Production/Stable
Classifier: License :: OSI Approved
Requires-Python: >=3.6
License-File: LICENSE
Requires-Dist: jsii (<2.0.0,>=1.52.1)
Requires-Dist: publication (>=0.0.3)
